[
  {
    "round": 1,
    "discussion": "Context-Aware Trend Expert (Leader): Thank you all for joining this discussion. Based on the downward trend I have identified, I strongly recommend selling at this point. The market is showing signs of a -2.34% decrease, and with recent major events increasing caution, it's important to act accordingly.\n\nMean Reversion Expert: I understand your point, but I believe that holding might be a more prudent strategy in this case. The price is near the mean, with a z-score of -0.79. This suggests that the current price is not too far off from its historical average, indicating stability.\n\nContext-Aware Volatility Expert: I agree with the hold recommendation. While there is medium volatility in the market, there is no clear signal to either buy or sell. Given the high volatility regime we are in due to the post-crisis recovery, low rates, and oil crash, holding might be the safer option.\n\nContext-Aware Sentiment Expert: I also lean towards holding in this situation. The market sentiment is neutral at 0.25, indicating a lack of strong positive or negative feelings. It might be wise to wait for more clarity before making any drastic moves.\n\nContext-Aware Trend Expert (Leader): I appreciate your inputs, but I still believe that selling is the best course of action. The downward trend we are seeing could indicate further losses ahead, especially with the cautious sentiment in the market. It's important to be proactive in times like these.\n\nMean Reversion Expert: I see your point, but I can't ignore the fact that the price is not significantly deviating from the mean. Holding might provide a buffer against potential losses while also giving us the opportunity to reassess the situation as it unfolds.\n\nContext-Aware Volatility Expert: I think we should consider the volatility factor as well. While holding might seem like a safe option, we need to be prepared for sudden shifts in the market. Selling could help mitigate some of that risk.\n\nContext-Aware Sentiment Expert: I agree with considering all factors, but I still believe that holding is the most balanced approach at the moment. It allows us to stay in the market while also being cautious about the potential downside.\n\nContext-Aware Trend Expert (Leader): It seems we have differing opinions on the best course of action. While I respect your viewpoints, I urge you to consider the implications of the downward trend and recent events on our decision. Selling might be a more defensive move in this uncertain market environment.\n\nMean Reversion Expert: I understand your concern, but I believe that holding aligns better with our historical data and current market conditions. It's important to weigh the risks and rewards carefully before making any decisions.\n\nContext-Aware Volatility Expert: I see merit in both selling and holding, but I lean towards holding as a more balanced approach. We need to be prepared for volatility but also consider the potential for market stability in the near term.\n\nContext-Aware Sentiment Expert: I agree with the need for a balanced approach. While the sentiment is neutral, we should be mindful of the broader market trends and volatility. Holding allows us to stay nimble while also avoiding knee-jerk reactions.\n\nContext-Aware Trend Expert (Leader): Thank you all for your insights. While we may not all agree on the best course of action, it's important to consider all perspectives before making a decision. Let's continue to monitor the market closely and revisit our strategies as needed.",
    "expert_analyses": {
      "Context-Aware Trend Expert": {
        "action": "sell",
        "confidence": 0.23756032542671052,
        "reason": "Downward trend detected: -2.34% decrease (Cautious selling in bull market: Post-crisis recovery, low rates, oil crash) (Recent major events increase caution)",
        "parameters": {
          "lookback_period": 10,
          "trend_threshold": 0.01
        },
        "context": {
          "year": "2014",
          "regime": "Post-crisis recovery, low rates, oil crash",
          "major_events": [
            {
              "date": "2014-07",
              "event": "European Central Bank cuts rates to combat deflation",
              "days_ago": -1
            }
          ],
          "risk_factors": [
            "Oil price volatility",
            "China slowdown",
            "Fed policy normalization"
          ],
          "market_sentiment_drivers": [
            "Central bank support",
            "Energy sector stress",
            "EM currency pressure"
          ]
        },
        "context_adjusted": true
      },
      "Mean Reversion Expert": {
        "action": "hold",
        "confidence": 0.5,
        "reason": "Price near mean (z-score: -0.79)",
        "parameters": {
          "window_size": 20,
          "std_dev_threshold": 1.5
        }
      },
      "Context-Aware Volatility Expert": {
        "action": "hold",
        "confidence": 0.6,
        "reason": "Medium volatility (0.74%), no clear signal (High volatility regime: Post-crisis recovery, low rates, oil crash)",
        "parameters": {
          "vol_window": 15,
          "high_vol_threshold": 0.015,
          "low_vol_threshold": 0.005
        },
        "context": {
          "year": "2014",
          "regime": "Post-crisis recovery, low rates, oil crash",
          "major_events": [
            {
              "date": "2014-07",
              "event": "European Central Bank cuts rates to combat deflation",
              "days_ago": -1
            }
          ],
          "risk_factors": [
            "Oil price volatility",
            "China slowdown",
            "Fed policy normalization"
          ],
          "market_sentiment_drivers": [
            "Central bank support",
            "Energy sector stress",
            "EM currency pressure"
          ]
        }
      },
      "Context-Aware Sentiment Expert": {
        "action": "hold",
        "confidence": 0.5,
        "reason": "Neutral market sentiment: 0.25",
        "parameters": {
          "sentiment_threshold": 0.6
        },
        "context": {
          "year": "2014",
          "regime": "Post-crisis recovery, low rates, oil crash",
          "major_events": [
            {
              "date": "2014-07",
              "event": "European Central Bank cuts rates to combat deflation",
              "days_ago": -1
            }
          ],
          "risk_factors": [
            "Oil price volatility",
            "China slowdown",
            "Fed policy normalization"
          ],
          "market_sentiment_drivers": [
            "Central bank support",
            "Energy sector stress",
            "EM currency pressure"
          ]
        }
      }
    }
  },
  {
    "round": "final",
    "consensus": {
      "action": "hold",
      "confidence": 0.5333333333333333,
      "supporting_experts": [
        "Mean Reversion Expert",
        "Context-Aware Volatility Expert",
        "Context-Aware Sentiment Expert"
      ],
      "reasons": [
        "Price near mean (z-score: -0.79)",
        "Medium volatility (0.74%), no clear signal (High volatility regime: Post-crisis recovery, low rates, oil crash)",
        "Neutral market sentiment: 0.25"
      ],
      "vote_ratio": 0.75
    }
  }
]